fastapi_simple_errors/__init__.py
fastapi_simple_errors/py.typed
fastapi_simple_errors-1.0.0.dist-info/LICENSE
fastapi_simple_errors-1.0.0.dist-info/METADATA
fastapi_simple_errors-1.0.0.dist-info/WHEEL
fastapi_simple_errors-1.0.0.dist-info/RECORD
