Metadata-Version: 2.1
Name: fastapi-simple-errors
Version: 1.0.0
Summary: Simple error handling for fastapi using custom error classes.
Home-page: https://github.com/patrsc/fastapi-simple-errors
License: MIT
Author: Patrick
Author-email: patrsc@nubu.at
Requires-Python: >=3.8.1,<4.0.0
Classifier: License :: OSI Approved :: MIT License
Classifier: Programming Language :: Python :: 3
Classifier: Programming Language :: Python :: 3.9
Classifier: Programming Language :: Python :: 3.10
Classifier: Programming Language :: Python :: 3.11
Requires-Dist: fastapi (>=0.115.0,<0.116.0)
Project-URL: Bug Tracker, https://github.com/patrsc/fastapi-simple-errors/issues
Project-URL: Documentation, https://github.com/patrsc/fastapi-simple-errors
Project-URL: Repository, https://github.com/patrsc/fastapi-simple-errors
